active_time_scheduling/__init__.py
active_time_scheduling/models/__init__.py
active_time_scheduling/models/job.py
active_time_scheduling/models/job_pool.py
active_time_scheduling/models/job_schedule.py
active_time_scheduling/models/schedule.py
active_time_scheduling/schedulers/__init__.py
active_time_scheduling/schedulers/abstract_scheduler.py
active_time_scheduling/schedulers/batch_scheduler.py
active_time_scheduling/schedulers/brute_force_scheduler.py
active_time_scheduling/schedulers/greedy_scheduler.py
active_time_scheduling/schedulers/lazy_activation_scheduler.py
active_time_scheduling/schedulers/linear_programming_scheduler.py
active_time_scheduling/schedulers/matching_scheduler.py
active_time_scheduling/utils/__init__.py
active_time_scheduling/utils/create_image.py
active_time_scheduling/utils/disjoint_set_node.py
active_time_scheduling/utils/maximum_flow.py
active_time_scheduling/utils/maximum_matching.py
active_time_scheduling-1.0.2.dist-info/LICENSE
active_time_scheduling-1.0.2.dist-info/METADATA
active_time_scheduling-1.0.2.dist-info/WHEEL
active_time_scheduling-1.0.2.dist-info/top_level.txt
active_time_scheduling-1.0.2.dist-info/RECORD
