Metadata-Version: 2.1
Name: active-time-scheduling
Version: 1.0.2
Summary: A collection of methods for Active Time Problem
Author-email: Nikita Kostin <nikita.kostin@tum.de>
License: MIT License        
Project-URL: Homepage, https://github.com/nikita-kostin/active-time-scheduling-package
Project-URL: Bug Tracker, https://github.com/nikita-kostin/active-time-scheduling-package/issues
Classifier: Programming Language :: Python :: 3
Classifier: License :: OSI Approved :: MIT License
Classifier: Operating System :: OS Independent
Requires-Python: >=3.8
License-File: LICENSE
Requires-Dist: attrs (==22.1.0)
Requires-Dist: cycler (==0.11.0)
Requires-Dist: daal (==2021.2.3)
Requires-Dist: fonttools (==4.37.0)
Requires-Dist: iniconfig (==1.1.1)
Requires-Dist: kiwisolver (==1.4.4)
Requires-Dist: matplotlib (==3.5.3)
Requires-Dist: networkx (==2.8.6)
Requires-Dist: numpy (==1.20.3)
Requires-Dist: packaging (==21.3)
Requires-Dist: Pillow (==9.2.0)
Requires-Dist: pluggy (==1.0.0)
Requires-Dist: py (==1.11.0)
Requires-Dist: pyparsing (==3.0.9)
Requires-Dist: pytest (==7.1.2)
Requires-Dist: pytest-repeat (==0.9.1)
Requires-Dist: python-dateutil (==2.8.2)
Requires-Dist: scipy (==1.9.0)
Requires-Dist: six (==1.16.0)
Requires-Dist: tomli (==2.0.1)
